cc_plugin_cc6/__init__.py
cc_plugin_cc6/_constants.py
cc_plugin_cc6/_version.py
cc_plugin_cc6/base.py
cc_plugin_cc6/cc6.py
cc_plugin_cc6/tables.py
cc_plugin_cc6/utils.py
cc_plugin_cc6-0.4.2.dist-info/licenses/LICENSE
cc_plugin_cc6-0.4.2.dist-info/METADATA
cc_plugin_cc6-0.4.2.dist-info/WHEEL
cc_plugin_cc6-0.4.2.dist-info/entry_points.txt
cc_plugin_cc6-0.4.2.dist-info/top_level.txt
cc_plugin_cc6-0.4.2.dist-info/RECORD
