Metadata-Version: 2.4
Name: cc-plugin-cc6
Version: 0.4.2
Summary: Compliance Checker CORDEX-CMIP6 plugin
Author-email: Martin Schupfner <schupfner@dkrz.de>, Lars Buntemeyer <lars.buntemeyer@hereon.de>
Maintainer-email: Lars Buntemeyer <lars.buntemeyer@hereon.de>, Martin Schupfner <schupfner@dkrz.de>
License:                                  Apache License
Project-URL: documentation, http://ioos.github.io/compliance-checker
Project-URL: homepage, https://github.com/euro-cordex/cc-plugin-cc6
Project-URL: repository, https://github.com/euro-cordex/cc-plugin-cc6
Keywords: compliance checker,plugin,cordex,cordex-cmip6
Classifier: Programming Language :: Python :: 3 :: Only
Classifier: Programming Language :: Python :: 3.10
Classifier: Programming Language :: Python :: 3.11
Classifier: Programming Language :: Python :: 3.12
Classifier: Programming Language :: Python :: 3.13
Requires-Python: >=3.10
License-File: LICENSE
Requires-Dist: cftime
Requires-Dist: cf_xarray
Requires-Dist: compliance-checker>=5.1.2
Requires-Dist: netCDF4
Requires-Dist: pandas
Requires-Dist: pooch
Requires-Dist: xarray
Provides-Extra: dev
Requires-Dist: black; extra == "dev"
Requires-Dist: bump2version; extra == "dev"
Requires-Dist: isort; extra == "dev"
Requires-Dist: flake8; extra == "dev"
Requires-Dist: flake8-builtins; extra == "dev"
Requires-Dist: flake8-comprehensions; extra == "dev"
Requires-Dist: flake8-mutable; extra == "dev"
Requires-Dist: flake8-print; extra == "dev"
Requires-Dist: gitpython; extra == "dev"
Requires-Dist: importlib_metadata; extra == "dev"
Requires-Dist: pre-commit; extra == "dev"
Requires-Dist: pytest>=7.0.0; extra == "dev"
Requires-Dist: pytest-flake8; extra == "dev"
Requires-Dist: ruff>=0.1.0; extra == "dev"
Dynamic: license-file
